{
  "section_id": "28-nvidia-cpo",
  "title": "Nvidia CPO",
  "title_translation": null,
  "paragraphs": [
    {
      "id": "p000",
      "index": 0,
      "source": "At GTC 2025, Nvidia debuted their first CPO-based switches for scale-out networks. Three different CPO-based switches were announced. We will walk through each of them in turn, but we first present a neat table aggregating all the important specifications:",
      "source_html": null,
      "element_type": "p",
      "inline_elements": [],
      "parent_block_id": "b0353",
      "parent_block_index": 353,
      "parent_block_type": "p",
      "parent_block_markdown": "At GTC 2025, Nvidia debuted their first CPO-based switches for scale-out networks. Three different CPO-based switches were announced. We will walk through each of them in turn, but we first present a neat table aggregating all the important specifications:",
      "parent_block_plain_text": "At GTC 2025, Nvidia debuted their first CPO-based switches for scale-out networks. Three different CPO-based switches were announced. We will walk through each of them in turn, but we first present a neat table aggregating all the important specifications:",
      "parent_source_html": null,
      "parent_inline_elements": [],
      "segment_start": 0,
      "segment_end": 256,
      "expected_tokens": [],
      "format_recovery_status": "not_applicable",
      "format_errors": [],
      "is_heading": false,
      "heading_level": null,
      "heading_chain": [],
      "is_metadata": false,
      "metadata_type": null,
      "translations": {},
      "confirmed": null,
      "confirmed_tokenized": null,
      "confirmed_format_issues": [],
      "status": "pending",
      "ai_insight": null,
      "history": []
    },
    {
      "id": "p001",
      "index": 1,
      "source": "![](./Co_Packaged_Optics_(CPO)_–_Scaling_with_Light_for_the_Next_Wave_of_Interconnect_images/img_045.png)",
      "source_html": "<img src=\"![](./Co_Packaged_Optics_(CPO)_–_Scaling_with_Light_for_the_Next_Wave_of_Interconnect_images/img_045.png)\" />",
      "element_type": "image",
      "inline_elements": [],
      "parent_block_id": "b0354",
      "parent_block_index": 354,
      "parent_block_type": "image",
      "parent_block_markdown": "![](./Co_Packaged_Optics_(CPO)_–_Scaling_with_Light_for_the_Next_Wave_of_Interconnect_images/img_045.png)",
      "parent_block_plain_text": "![](./Co_Packaged_Optics_(CPO)_–_Scaling_with_Light_for_the_Next_Wave_of_Interconnect_images/img_045.png)",
      "parent_source_html": "<img src=\"![](./Co_Packaged_Optics_(CPO)_–_Scaling_with_Light_for_the_Next_Wave_of_Interconnect_images/img_045.png)\" />",
      "parent_inline_elements": [],
      "segment_start": 0,
      "segment_end": 105,
      "expected_tokens": [],
      "format_recovery_status": "not_applicable",
      "format_errors": [],
      "is_heading": false,
      "heading_level": null,
      "heading_chain": [],
      "is_metadata": true,
      "metadata_type": "image",
      "translations": {},
      "confirmed": "![](./Co_Packaged_Optics_(CPO)_–_Scaling_with_Light_for_the_Next_Wave_of_Interconnect_images/img_045.png)",
      "confirmed_tokenized": null,
      "confirmed_format_issues": [],
      "status": "approved",
      "ai_insight": null,
      "history": []
    },
    {
      "id": "p002",
      "index": 2,
      "source": "Source: SemiAnalysis",
      "source_html": null,
      "element_type": "p",
      "inline_elements": [],
      "parent_block_id": "b0355",
      "parent_block_index": 355,
      "parent_block_type": "p",
      "parent_block_markdown": "Source: SemiAnalysis",
      "parent_block_plain_text": "Source: SemiAnalysis",
      "parent_source_html": null,
      "parent_inline_elements": [],
      "segment_start": 0,
      "segment_end": 20,
      "expected_tokens": [],
      "format_recovery_status": "not_applicable",
      "format_errors": [],
      "is_heading": false,
      "heading_level": null,
      "heading_chain": [],
      "is_metadata": true,
      "metadata_type": "source",
      "translations": {},
      "confirmed": null,
      "confirmed_tokenized": null,
      "confirmed_format_issues": [],
      "status": "pending",
      "ai_insight": null,
      "history": []
    },
    {
      "id": "p003",
      "index": 3,
      "source": "Quantum-X Photonics",
      "source_html": null,
      "element_type": "h3",
      "inline_elements": [],
      "parent_block_id": "b0356",
      "parent_block_index": 356,
      "parent_block_type": "h3",
      "parent_block_markdown": "### Quantum-X Photonics",
      "parent_block_plain_text": "Quantum-X Photonics",
      "parent_source_html": null,
      "parent_inline_elements": [],
      "segment_start": 0,
      "segment_end": 19,
      "expected_tokens": [],
      "format_recovery_status": "not_applicable",
      "format_errors": [],
      "is_heading": true,
      "heading_level": 3,
      "heading_chain": [],
      "is_metadata": false,
      "metadata_type": null,
      "translations": {},
      "confirmed": null,
      "confirmed_tokenized": null,
      "confirmed_format_issues": [],
      "status": "pending",
      "ai_insight": null,
      "history": []
    },
    {
      "id": "p004",
      "index": 4,
      "source": "The first CPO switch to come to market by 2H 2025 will be the Quantum X800-Q3450. It features 144 Physical MPO ports which enables 144 logical ports of 800G or 72 logical ports of 1.6T, for aggregate bandwidth of 115.2T. Its resemblance to a spaghetti monster has the authors’ stomachs rumbling.",
      "source_html": null,
      "element_type": "p",
      "inline_elements": [],
      "parent_block_id": "b0357",
      "parent_block_index": 357,
      "parent_block_type": "p",
      "parent_block_markdown": "The first CPO switch to come to market by 2H 2025 will be the Quantum X800-Q3450. It features 144 Physical MPO ports which enables 144 logical ports of 800G or 72 logical ports of 1.6T, for aggregate bandwidth of 115.2T. Its resemblance to a spaghetti monster has the authors’ stomachs rumbling.",
      "parent_block_plain_text": "The first CPO switch to come to market by 2H 2025 will be the Quantum X800-Q3450. It features 144 Physical MPO ports which enables 144 logical ports of 800G or 72 logical ports of 1.6T, for aggregate bandwidth of 115.2T. Its resemblance to a spaghetti monster has the authors’ stomachs rumbling.",
      "parent_source_html": null,
      "parent_inline_elements": [],
      "segment_start": 0,
      "segment_end": 295,
      "expected_tokens": [],
      "format_recovery_status": "not_applicable",
      "format_errors": [],
      "is_heading": false,
      "heading_level": null,
      "heading_chain": [],
      "is_metadata": false,
      "metadata_type": null,
      "translations": {},
      "confirmed": null,
      "confirmed_tokenized": null,
      "confirmed_format_issues": [],
      "status": "pending",
      "ai_insight": null,
      "history": []
    },
    {
      "id": "p005",
      "index": 5,
      "source": "![](./Co_Packaged_Optics_(CPO)_–_Scaling_with_Light_for_the_Next_Wave_of_Interconnect_images/img_046.png)",
      "source_html": "<img src=\"![](./Co_Packaged_Optics_(CPO)_–_Scaling_with_Light_for_the_Next_Wave_of_Interconnect_images/img_046.png)\" />",
      "element_type": "image",
      "inline_elements": [],
      "parent_block_id": "b0358",
      "parent_block_index": 358,
      "parent_block_type": "image",
      "parent_block_markdown": "![](./Co_Packaged_Optics_(CPO)_–_Scaling_with_Light_for_the_Next_Wave_of_Interconnect_images/img_046.png)",
      "parent_block_plain_text": "![](./Co_Packaged_Optics_(CPO)_–_Scaling_with_Light_for_the_Next_Wave_of_Interconnect_images/img_046.png)",
      "parent_source_html": "<img src=\"![](./Co_Packaged_Optics_(CPO)_–_Scaling_with_Light_for_the_Next_Wave_of_Interconnect_images/img_046.png)\" />",
      "parent_inline_elements": [],
      "segment_start": 0,
      "segment_end": 105,
      "expected_tokens": [],
      "format_recovery_status": "not_applicable",
      "format_errors": [],
      "is_heading": false,
      "heading_level": null,
      "heading_chain": [],
      "is_metadata": true,
      "metadata_type": "image",
      "translations": {},
      "confirmed": "![](./Co_Packaged_Optics_(CPO)_–_Scaling_with_Light_for_the_Next_Wave_of_Interconnect_images/img_046.png)",
      "confirmed_tokenized": null,
      "confirmed_format_issues": [],
      "status": "approved",
      "ai_insight": null,
      "history": []
    },
    {
      "id": "p006",
      "index": 6,
      "source": "Source: Nvidia",
      "source_html": null,
      "element_type": "p",
      "inline_elements": [],
      "parent_block_id": "b0359",
      "parent_block_index": 359,
      "parent_block_type": "p",
      "parent_block_markdown": "Source: Nvidia",
      "parent_block_plain_text": "Source: Nvidia",
      "parent_source_html": null,
      "parent_inline_elements": [],
      "segment_start": 0,
      "segment_end": 14,
      "expected_tokens": [],
      "format_recovery_status": "not_applicable",
      "format_errors": [],
      "is_heading": false,
      "heading_level": null,
      "heading_chain": [],
      "is_metadata": true,
      "metadata_type": "source",
      "translations": {},
      "confirmed": null,
      "confirmed_tokenized": null,
      "confirmed_format_issues": [],
      "status": "pending",
      "ai_insight": null,
      "history": []
    },
    {
      "id": "p007",
      "index": 7,
      "source": "The Quantum X800-Q3450 achieves this high radix and high aggregate bandwidth by using four Quantum-X800 ASIC chips with 28.8 Tbit/s bandwidth each in a multi-plane configuration. In this multi-plane configuration, each physical port is connected to each of the four switch ASICs, allowing any physical port to talk to another one by spraying the data across all four 200G lanes via the four different switch ASICs.",
      "source_html": null,
      "element_type": "p",
      "inline_elements": [],
      "parent_block_id": "b0360",
      "parent_block_index": 360,
      "parent_block_type": "p",
      "parent_block_markdown": "The Quantum X800-Q3450 achieves this high radix and high aggregate bandwidth by using four Quantum-X800 ASIC chips with 28.8 Tbit/s bandwidth each in a multi-plane configuration. In this multi-plane configuration, each physical port is connected to each of the four switch ASICs, allowing any physical port to talk to another one by spraying the data across all four 200G lanes via the four different switch ASICs.",
      "parent_block_plain_text": "The Quantum X800-Q3450 achieves this high radix and high aggregate bandwidth by using four Quantum-X800 ASIC chips with 28.8 Tbit/s bandwidth each in a multi-plane configuration. In this multi-plane configuration, each physical port is connected to each of the four switch ASICs, allowing any physical port to talk to another one by spraying the data across all four 200G lanes via the four different switch ASICs.",
      "parent_source_html": null,
      "parent_inline_elements": [],
      "segment_start": 0,
      "segment_end": 414,
      "expected_tokens": [],
      "format_recovery_status": "not_applicable",
      "format_errors": [],
      "is_heading": false,
      "heading_level": null,
      "heading_chain": [],
      "is_metadata": false,
      "metadata_type": null,
      "translations": {},
      "confirmed": null,
      "confirmed_tokenized": null,
      "confirmed_format_issues": [],
      "status": "pending",
      "ai_insight": null,
      "history": []
    },
    {
      "id": "p008",
      "index": 8,
      "source": "When it comes to the maximum cluster size for a three-layer network, this delivers the same end result as theoretically using four times as many 28.8T switch boxes but with 200G logical port sizes – both allow a maximum cluster size of 746,496 GPUs. This difference is that when using the X800-Q3400 switch, the shuffle happens neatly inside the switch box, while setting up the same network with discrete 28.8T switch boxes will require far more individual fiber cables going to a greater number of destinations.",
      "source_html": null,
      "element_type": "p",
      "inline_elements": [],
      "parent_block_id": "b0361",
      "parent_block_index": 361,
      "parent_block_type": "p",
      "parent_block_markdown": "When it comes to the maximum cluster size for a three-layer network, this delivers the same end result as theoretically using four times as many 28.8T switch boxes but with 200G logical port sizes – both allow a maximum cluster size of 746,496 GPUs. This difference is that when using the X800-Q3400 switch, the shuffle happens neatly inside the switch box, while setting up the same network with discrete 28.8T switch boxes will require far more individual fiber cables going to a greater number of destinations.",
      "parent_block_plain_text": "When it comes to the maximum cluster size for a three-layer network, this delivers the same end result as theoretically using four times as many 28.8T switch boxes but with 200G logical port sizes – both allow a maximum cluster size of 746,496 GPUs. This difference is that when using the X800-Q3400 switch, the shuffle happens neatly inside the switch box, while setting up the same network with discrete 28.8T switch boxes will require far more individual fiber cables going to a greater number of destinations.",
      "parent_source_html": null,
      "parent_inline_elements": [],
      "segment_start": 0,
      "segment_end": 513,
      "expected_tokens": [],
      "format_recovery_status": "not_applicable",
      "format_errors": [],
      "is_heading": false,
      "heading_level": null,
      "heading_chain": [],
      "is_metadata": false,
      "metadata_type": null,
      "translations": {},
      "confirmed": null,
      "confirmed_tokenized": null,
      "confirmed_format_issues": [],
      "status": "pending",
      "ai_insight": null,
      "history": []
    },
    {
      "id": "p009",
      "index": 9,
      "source": "![](./Co_Packaged_Optics_(CPO)_–_Scaling_with_Light_for_the_Next_Wave_of_Interconnect_images/img_047.png)",
      "source_html": "<img src=\"![](./Co_Packaged_Optics_(CPO)_–_Scaling_with_Light_for_the_Next_Wave_of_Interconnect_images/img_047.png)\" />",
      "element_type": "image",
      "inline_elements": [],
      "parent_block_id": "b0362",
      "parent_block_index": 362,
      "parent_block_type": "image",
      "parent_block_markdown": "![](./Co_Packaged_Optics_(CPO)_–_Scaling_with_Light_for_the_Next_Wave_of_Interconnect_images/img_047.png)",
      "parent_block_plain_text": "![](./Co_Packaged_Optics_(CPO)_–_Scaling_with_Light_for_the_Next_Wave_of_Interconnect_images/img_047.png)",
      "parent_source_html": "<img src=\"![](./Co_Packaged_Optics_(CPO)_–_Scaling_with_Light_for_the_Next_Wave_of_Interconnect_images/img_047.png)\" />",
      "parent_inline_elements": [],
      "segment_start": 0,
      "segment_end": 105,
      "expected_tokens": [],
      "format_recovery_status": "not_applicable",
      "format_errors": [],
      "is_heading": false,
      "heading_level": null,
      "heading_chain": [],
      "is_metadata": true,
      "metadata_type": "image",
      "translations": {},
      "confirmed": "![](./Co_Packaged_Optics_(CPO)_–_Scaling_with_Light_for_the_Next_Wave_of_Interconnect_images/img_047.png)",
      "confirmed_tokenized": null,
      "confirmed_format_issues": [],
      "status": "approved",
      "ai_insight": null,
      "history": []
    },
    {
      "id": "p010",
      "index": 10,
      "source": "Source: SemiAnalysis",
      "source_html": null,
      "element_type": "p",
      "inline_elements": [],
      "parent_block_id": "b0363",
      "parent_block_index": 363,
      "parent_block_type": "p",
      "parent_block_markdown": "Source: SemiAnalysis",
      "parent_block_plain_text": "Source: SemiAnalysis",
      "parent_source_html": null,
      "parent_inline_elements": [],
      "segment_start": 0,
      "segment_end": 20,
      "expected_tokens": [],
      "format_recovery_status": "not_applicable",
      "format_errors": [],
      "is_heading": false,
      "heading_level": null,
      "heading_chain": [],
      "is_metadata": true,
      "metadata_type": "source",
      "translations": {},
      "confirmed": null,
      "confirmed_tokenized": null,
      "confirmed_format_issues": [],
      "status": "pending",
      "ai_insight": null,
      "history": []
    },
    {
      "id": "p011",
      "index": 11,
      "source": "Each ASIC in the Quantum-X800-Q3450 is surrounded by six detachable optical sub-assemblies, with each sub-assembly housing three optical engines. Each optical engine delivers 1.6 Tbit/s of bandwidth, resulting in a total of 18 optical engines per ASIC and an aggregate optical bandwidth of 28.8 Tbit/s per ASIC. Note that these sub-assemblies are detachable, so purists may consider this to be technically “NPO” not strictly “CPO.” While there is a bit of extra signal loss associated with the detachable OE, in effect we believe this will not considerably impact performance.",
      "source_html": null,
      "element_type": "p",
      "inline_elements": [],
      "parent_block_id": "b0364",
      "parent_block_index": 364,
      "parent_block_type": "p",
      "parent_block_markdown": "Each ASIC in the Quantum-X800-Q3450 is surrounded by six detachable optical sub-assemblies, with each sub-assembly housing three optical engines. Each optical engine delivers 1.6 Tbit/s of bandwidth, resulting in a total of 18 optical engines per ASIC and an aggregate optical bandwidth of 28.8 Tbit/s per ASIC. Note that these sub-assemblies are detachable, so purists may consider this to be technically “NPO” not strictly “CPO.” While there is a bit of extra signal loss associated with the detachable OE, in effect we believe this will not considerably impact performance.",
      "parent_block_plain_text": "Each ASIC in the Quantum-X800-Q3450 is surrounded by six detachable optical sub-assemblies, with each sub-assembly housing three optical engines. Each optical engine delivers 1.6 Tbit/s of bandwidth, resulting in a total of 18 optical engines per ASIC and an aggregate optical bandwidth of 28.8 Tbit/s per ASIC. Note that these sub-assemblies are detachable, so purists may consider this to be technically “NPO” not strictly “CPO.” While there is a bit of extra signal loss associated with the detachable OE, in effect we believe this will not considerably impact performance.",
      "parent_source_html": null,
      "parent_inline_elements": [],
      "segment_start": 0,
      "segment_end": 576,
      "expected_tokens": [],
      "format_recovery_status": "not_applicable",
      "format_errors": [],
      "is_heading": false,
      "heading_level": null,
      "heading_chain": [],
      "is_metadata": false,
      "metadata_type": null,
      "translations": {},
      "confirmed": null,
      "confirmed_tokenized": null,
      "confirmed_format_issues": [],
      "status": "pending",
      "ai_insight": null,
      "history": []
    },
    {
      "id": "p012",
      "index": 12,
      "source": "![](./Co_Packaged_Optics_(CPO)_–_Scaling_with_Light_for_the_Next_Wave_of_Interconnect_images/img_048.png)",
      "source_html": "<img src=\"![](./Co_Packaged_Optics_(CPO)_–_Scaling_with_Light_for_the_Next_Wave_of_Interconnect_images/img_048.png)\" />",
      "element_type": "image",
      "inline_elements": [],
      "parent_block_id": "b0365",
      "parent_block_index": 365,
      "parent_block_type": "image",
      "parent_block_markdown": "![](./Co_Packaged_Optics_(CPO)_–_Scaling_with_Light_for_the_Next_Wave_of_Interconnect_images/img_048.png)",
      "parent_block_plain_text": "![](./Co_Packaged_Optics_(CPO)_–_Scaling_with_Light_for_the_Next_Wave_of_Interconnect_images/img_048.png)",
      "parent_source_html": "<img src=\"![](./Co_Packaged_Optics_(CPO)_–_Scaling_with_Light_for_the_Next_Wave_of_Interconnect_images/img_048.png)\" />",
      "parent_inline_elements": [],
      "segment_start": 0,
      "segment_end": 105,
      "expected_tokens": [],
      "format_recovery_status": "not_applicable",
      "format_errors": [],
      "is_heading": false,
      "heading_level": null,
      "heading_chain": [],
      "is_metadata": true,
      "metadata_type": "image",
      "translations": {},
      "confirmed": "![](./Co_Packaged_Optics_(CPO)_–_Scaling_with_Light_for_the_Next_Wave_of_Interconnect_images/img_048.png)",
      "confirmed_tokenized": null,
      "confirmed_format_issues": [],
      "status": "approved",
      "ai_insight": null,
      "history": []
    },
    {
      "id": "p013",
      "index": 13,
      "source": "Source: Nvidia",
      "source_html": null,
      "element_type": "p",
      "inline_elements": [],
      "parent_block_id": "b0366",
      "parent_block_index": 366,
      "parent_block_type": "p",
      "parent_block_markdown": "Source: Nvidia",
      "parent_block_plain_text": "Source: Nvidia",
      "parent_source_html": null,
      "parent_inline_elements": [],
      "segment_start": 0,
      "segment_end": 14,
      "expected_tokens": [],
      "format_recovery_status": "not_applicable",
      "format_errors": [],
      "is_heading": false,
      "heading_level": null,
      "heading_chain": [],
      "is_metadata": true,
      "metadata_type": "source",
      "translations": {},
      "confirmed": null,
      "confirmed_tokenized": null,
      "confirmed_format_issues": [],
      "status": "pending",
      "ai_insight": null,
      "history": []
    },
    {
      "id": "p014",
      "index": 14,
      "source": "Each engine operates with 8 electrical and optical channels, driven by 200G PAM4 SerDes on the electrical side and on the optical side, 8 Micro-Ring Modulators (MRMs) use PAM4 modulation to achieve 200G per modulator. This design choice was one of the big takeaways of the announcement: that Nvidia and TSMC can ship 200G MRMs in production. This matches the fastest MZMs today and disproves the industry notion that MRMs are limited to NRZ modulation. It’s quite an impressive engineering achievement by Nvidia to reach this milestone.",
      "source_html": null,
      "element_type": "p",
      "inline_elements": [],
      "parent_block_id": "b0367",
      "parent_block_index": 367,
      "parent_block_type": "p",
      "parent_block_markdown": "Each engine operates with 8 electrical and optical channels, driven by 200G PAM4 SerDes on the electrical side and on the optical side, 8 Micro-Ring Modulators (MRMs) use PAM4 modulation to achieve 200G per modulator. This design choice was one of the big takeaways of the announcement: that Nvidia and TSMC can ship 200G MRMs in production. This matches the fastest MZMs today and disproves the industry notion that MRMs are limited to NRZ modulation. It’s quite an impressive engineering achievement by Nvidia to reach this milestone.",
      "parent_block_plain_text": "Each engine operates with 8 electrical and optical channels, driven by 200G PAM4 SerDes on the electrical side and on the optical side, 8 Micro-Ring Modulators (MRMs) use PAM4 modulation to achieve 200G per modulator. This design choice was one of the big takeaways of the announcement: that Nvidia and TSMC can ship 200G MRMs in production. This matches the fastest MZMs today and disproves the industry notion that MRMs are limited to NRZ modulation. It’s quite an impressive engineering achievement by Nvidia to reach this milestone.",
      "parent_source_html": null,
      "parent_inline_elements": [],
      "segment_start": 0,
      "segment_end": 536,
      "expected_tokens": [],
      "format_recovery_status": "not_applicable",
      "format_errors": [],
      "is_heading": false,
      "heading_level": null,
      "heading_chain": [],
      "is_metadata": false,
      "metadata_type": null,
      "translations": {},
      "confirmed": null,
      "confirmed_tokenized": null,
      "confirmed_format_issues": [],
      "status": "pending",
      "ai_insight": null,
      "history": []
    },
    {
      "id": "p015",
      "index": 15,
      "source": "![](./Co_Packaged_Optics_(CPO)_–_Scaling_with_Light_for_the_Next_Wave_of_Interconnect_images/img_049.png)",
      "source_html": "<img src=\"![](./Co_Packaged_Optics_(CPO)_–_Scaling_with_Light_for_the_Next_Wave_of_Interconnect_images/img_049.png)\" />",
      "element_type": "image",
      "inline_elements": [],
      "parent_block_id": "b0368",
      "parent_block_index": 368,
      "parent_block_type": "image",
      "parent_block_markdown": "![](./Co_Packaged_Optics_(CPO)_–_Scaling_with_Light_for_the_Next_Wave_of_Interconnect_images/img_049.png)",
      "parent_block_plain_text": "![](./Co_Packaged_Optics_(CPO)_–_Scaling_with_Light_for_the_Next_Wave_of_Interconnect_images/img_049.png)",
      "parent_source_html": "<img src=\"![](./Co_Packaged_Optics_(CPO)_–_Scaling_with_Light_for_the_Next_Wave_of_Interconnect_images/img_049.png)\" />",
      "parent_inline_elements": [],
      "segment_start": 0,
      "segment_end": 105,
      "expected_tokens": [],
      "format_recovery_status": "not_applicable",
      "format_errors": [],
      "is_heading": false,
      "heading_level": null,
      "heading_chain": [],
      "is_metadata": true,
      "metadata_type": "image",
      "translations": {},
      "confirmed": "![](./Co_Packaged_Optics_(CPO)_–_Scaling_with_Light_for_the_Next_Wave_of_Interconnect_images/img_049.png)",
      "confirmed_tokenized": null,
      "confirmed_format_issues": [],
      "status": "approved",
      "ai_insight": null,
      "history": []
    },
    {
      "id": "p016",
      "index": 16,
      "source": "Source: Nvidia",
      "source_html": null,
      "element_type": "p",
      "inline_elements": [],
      "parent_block_id": "b0369",
      "parent_block_index": 369,
      "parent_block_type": "p",
      "parent_block_markdown": "Source: Nvidia",
      "parent_block_plain_text": "Source: Nvidia",
      "parent_source_html": null,
      "parent_inline_elements": [],
      "segment_start": 0,
      "segment_end": 14,
      "expected_tokens": [],
      "format_recovery_status": "not_applicable",
      "format_errors": [],
      "is_heading": false,
      "heading_level": null,
      "heading_chain": [],
      "is_metadata": true,
      "metadata_type": "source",
      "translations": {},
      "confirmed": null,
      "confirmed_tokenized": null,
      "confirmed_format_issues": [],
      "status": "pending",
      "ai_insight": null,
      "history": []
    },
    {
      "id": "p017",
      "index": 17,
      "source": "Each optical engine integrates a Photonic Integrated Circuit (PIC) built on a mature N65 process node, and an Electronic Integrated Circuit (EIC) fabricated on an advanced N6 node. The PIC leverages the older node because it contains optical components such as modulators, waveguides, and detectors—devices that do not benefit from scaling, and often perform better at larger geometries. In contrast, the EIC includes drivers, TIAs, and control logic, which benefit significantly from higher transistor density and improved power efficiency enabled by advanced nodes. These two dies are then hybrid bonded using TSMC’s COUPE platform, enabling ultra-short, high-bandwidth interconnects between the photonic and electronic domains.",
      "source_html": null,
      "element_type": "p",
      "inline_elements": [],
      "parent_block_id": "b0370",
      "parent_block_index": 370,
      "parent_block_type": "p",
      "parent_block_markdown": "Each optical engine integrates a Photonic Integrated Circuit (PIC) built on a mature N65 process node, and an Electronic Integrated Circuit (EIC) fabricated on an advanced N6 node. The PIC leverages the older node because it contains optical components such as modulators, waveguides, and detectors—devices that do not benefit from scaling, and often perform better at larger geometries. In contrast, the EIC includes drivers, TIAs, and control logic, which benefit significantly from higher transistor density and improved power efficiency enabled by advanced nodes. These two dies are then hybrid bonded using TSMC’s COUPE platform, enabling ultra-short, high-bandwidth interconnects between the photonic and electronic domains.",
      "parent_block_plain_text": "Each optical engine integrates a Photonic Integrated Circuit (PIC) built on a mature N65 process node, and an Electronic Integrated Circuit (EIC) fabricated on an advanced N6 node. The PIC leverages the older node because it contains optical components such as modulators, waveguides, and detectors—devices that do not benefit from scaling, and often perform better at larger geometries. In contrast, the EIC includes drivers, TIAs, and control logic, which benefit significantly from higher transistor density and improved power efficiency enabled by advanced nodes. These two dies are then hybrid bonded using TSMC’s COUPE platform, enabling ultra-short, high-bandwidth interconnects between the photonic and electronic domains.",
      "parent_source_html": null,
      "parent_inline_elements": [],
      "segment_start": 0,
      "segment_end": 730,
      "expected_tokens": [],
      "format_recovery_status": "not_applicable",
      "format_errors": [],
      "is_heading": false,
      "heading_level": null,
      "heading_chain": [],
      "is_metadata": false,
      "metadata_type": null,
      "translations": {},
      "confirmed": null,
      "confirmed_tokenized": null,
      "confirmed_format_issues": [],
      "status": "pending",
      "ai_insight": null,
      "history": []
    },
    {
      "id": "p018",
      "index": 18,
      "source": "![](./Co_Packaged_Optics_(CPO)_–_Scaling_with_Light_for_the_Next_Wave_of_Interconnect_images/img_050.png)",
      "source_html": "<img src=\"![](./Co_Packaged_Optics_(CPO)_–_Scaling_with_Light_for_the_Next_Wave_of_Interconnect_images/img_050.png)\" />",
      "element_type": "image",
      "inline_elements": [],
      "parent_block_id": "b0371",
      "parent_block_index": 371,
      "parent_block_type": "image",
      "parent_block_markdown": "![](./Co_Packaged_Optics_(CPO)_–_Scaling_with_Light_for_the_Next_Wave_of_Interconnect_images/img_050.png)",
      "parent_block_plain_text": "![](./Co_Packaged_Optics_(CPO)_–_Scaling_with_Light_for_the_Next_Wave_of_Interconnect_images/img_050.png)",
      "parent_source_html": "<img src=\"![](./Co_Packaged_Optics_(CPO)_–_Scaling_with_Light_for_the_Next_Wave_of_Interconnect_images/img_050.png)\" />",
      "parent_inline_elements": [],
      "segment_start": 0,
      "segment_end": 105,
      "expected_tokens": [],
      "format_recovery_status": "not_applicable",
      "format_errors": [],
      "is_heading": false,
      "heading_level": null,
      "heading_chain": [],
      "is_metadata": true,
      "metadata_type": "image",
      "translations": {},
      "confirmed": "![](./Co_Packaged_Optics_(CPO)_–_Scaling_with_Light_for_the_Next_Wave_of_Interconnect_images/img_050.png)",
      "confirmed_tokenized": null,
      "confirmed_format_issues": [],
      "status": "approved",
      "ai_insight": null,
      "history": []
    },
    {
      "id": "p019",
      "index": 19,
      "source": "Source: Nvidia",
      "source_html": null,
      "element_type": "p",
      "inline_elements": [],
      "parent_block_id": "b0372",
      "parent_block_index": 372,
      "parent_block_type": "p",
      "parent_block_markdown": "Source: Nvidia",
      "parent_block_plain_text": "Source: Nvidia",
      "parent_source_html": null,
      "parent_inline_elements": [],
      "segment_start": 0,
      "segment_end": 14,
      "expected_tokens": [],
      "format_recovery_status": "not_applicable",
      "format_errors": [],
      "is_heading": false,
      "heading_level": null,
      "heading_chain": [],
      "is_metadata": true,
      "metadata_type": "source",
      "translations": {},
      "confirmed": null,
      "confirmed_tokenized": null,
      "confirmed_format_issues": [],
      "status": "pending",
      "ai_insight": null,
      "history": []
    },
    {
      "id": "p020",
      "index": 20,
      "source": "Two copper cold plates sit atop the ASICs in the Quantum-X800-Q3450 as part of a closed-loop liquid cooling system that efficiently dissipates heat from each of the switch ASICs. The black tubing connected to the cold plates circulates coolant fluid, helping to maintain thermal stability. This cooling system is essential in maintaining thermal stability not only for the ASICs but also for the adjacent, temperature-sensitive co-packaged optics.",
      "source_html": null,
      "element_type": "p",
      "inline_elements": [],
      "parent_block_id": "b0373",
      "parent_block_index": 373,
      "parent_block_type": "p",
      "parent_block_markdown": "Two copper cold plates sit atop the ASICs in the Quantum-X800-Q3450 as part of a closed-loop liquid cooling system that efficiently dissipates heat from each of the switch ASICs. The black tubing connected to the cold plates circulates coolant fluid, helping to maintain thermal stability. This cooling system is essential in maintaining thermal stability not only for the ASICs but also for the adjacent, temperature-sensitive co-packaged optics.",
      "parent_block_plain_text": "Two copper cold plates sit atop the ASICs in the Quantum-X800-Q3450 as part of a closed-loop liquid cooling system that efficiently dissipates heat from each of the switch ASICs. The black tubing connected to the cold plates circulates coolant fluid, helping to maintain thermal stability. This cooling system is essential in maintaining thermal stability not only for the ASICs but also for the adjacent, temperature-sensitive co-packaged optics.",
      "parent_source_html": null,
      "parent_inline_elements": [],
      "segment_start": 0,
      "segment_end": 447,
      "expected_tokens": [],
      "format_recovery_status": "not_applicable",
      "format_errors": [],
      "is_heading": false,
      "heading_level": null,
      "heading_chain": [],
      "is_metadata": false,
      "metadata_type": null,
      "translations": {},
      "confirmed": null,
      "confirmed_tokenized": null,
      "confirmed_format_issues": [],
      "status": "pending",
      "ai_insight": null,
      "history": []
    },
    {
      "id": "p021",
      "index": 21,
      "source": "![](./Co_Packaged_Optics_(CPO)_–_Scaling_with_Light_for_the_Next_Wave_of_Interconnect_images/img_051.png)",
      "source_html": "<img src=\"![](./Co_Packaged_Optics_(CPO)_–_Scaling_with_Light_for_the_Next_Wave_of_Interconnect_images/img_051.png)\" />",
      "element_type": "image",
      "inline_elements": [],
      "parent_block_id": "b0374",
      "parent_block_index": 374,
      "parent_block_type": "image",
      "parent_block_markdown": "![](./Co_Packaged_Optics_(CPO)_–_Scaling_with_Light_for_the_Next_Wave_of_Interconnect_images/img_051.png)",
      "parent_block_plain_text": "![](./Co_Packaged_Optics_(CPO)_–_Scaling_with_Light_for_the_Next_Wave_of_Interconnect_images/img_051.png)",
      "parent_source_html": "<img src=\"![](./Co_Packaged_Optics_(CPO)_–_Scaling_with_Light_for_the_Next_Wave_of_Interconnect_images/img_051.png)\" />",
      "parent_inline_elements": [],
      "segment_start": 0,
      "segment_end": 105,
      "expected_tokens": [],
      "format_recovery_status": "not_applicable",
      "format_errors": [],
      "is_heading": false,
      "heading_level": null,
      "heading_chain": [],
      "is_metadata": true,
      "metadata_type": "image",
      "translations": {},
      "confirmed": "![](./Co_Packaged_Optics_(CPO)_–_Scaling_with_Light_for_the_Next_Wave_of_Interconnect_images/img_051.png)",
      "confirmed_tokenized": null,
      "confirmed_format_issues": [],
      "status": "approved",
      "ai_insight": null,
      "history": []
    },
    {
      "id": "p022",
      "index": 22,
      "source": "Source: Nvidia",
      "source_html": null,
      "element_type": "p",
      "inline_elements": [],
      "parent_block_id": "b0375",
      "parent_block_index": 375,
      "parent_block_type": "p",
      "parent_block_markdown": "Source: Nvidia",
      "parent_block_plain_text": "Source: Nvidia",
      "parent_source_html": null,
      "parent_inline_elements": [],
      "segment_start": 0,
      "segment_end": 14,
      "expected_tokens": [],
      "format_recovery_status": "not_applicable",
      "format_errors": [],
      "is_heading": false,
      "heading_level": null,
      "heading_chain": [],
      "is_metadata": true,
      "metadata_type": "source",
      "translations": {},
      "confirmed": null,
      "confirmed_tokenized": null,
      "confirmed_format_issues": [],
      "status": "pending",
      "ai_insight": null,
      "history": []
    },
    {
      "id": "p023",
      "index": 23,
      "source": "Spectrum-X Photonics",
      "source_html": null,
      "element_type": "h3",
      "inline_elements": [],
      "parent_block_id": "b0376",
      "parent_block_index": 376,
      "parent_block_type": "h3",
      "parent_block_markdown": "### Spectrum-X Photonics",
      "parent_block_plain_text": "Spectrum-X Photonics",
      "parent_source_html": null,
      "parent_inline_elements": [],
      "segment_start": 0,
      "segment_end": 20,
      "expected_tokens": [],
      "format_recovery_status": "not_applicable",
      "format_errors": [],
      "is_heading": true,
      "heading_level": 3,
      "heading_chain": [],
      "is_metadata": false,
      "metadata_type": null,
      "translations": {},
      "confirmed": null,
      "confirmed_tokenized": null,
      "confirmed_format_issues": [],
      "status": "pending",
      "ai_insight": null,
      "history": []
    },
    {
      "id": "p024",
      "index": 24,
      "source": "Spectrum-X Photonics is set for release in the 2nd half of 2026, with two separate switch configurations products to be released, an Ethernet Spectrum-X variant of the X800-Q3450 CPO switch with 102.4T aggregate bandwidth, the Spectrum 6810 offering 102.4T aggregate bandwidth, and its larger cousin the Spectrum 6800 offering 409.6T aggregate bandwidth by using four discrete Spectrum-6 multi-chip modules (MCMs).",
      "source_html": null,
      "element_type": "p",
      "inline_elements": [],
      "parent_block_id": "b0377",
      "parent_block_index": 377,
      "parent_block_type": "p",
      "parent_block_markdown": "Spectrum-X Photonics is set for release in the 2nd half of 2026, with two separate switch configurations products to be released, an Ethernet Spectrum-X variant of the X800-Q3450 CPO switch with 102.4T aggregate bandwidth, the Spectrum 6810 offering 102.4T aggregate bandwidth, and its larger cousin the Spectrum 6800 offering 409.6T aggregate bandwidth by using four discrete Spectrum-6 multi-chip modules (MCMs).",
      "parent_block_plain_text": "Spectrum-X Photonics is set for release in the 2nd half of 2026, with two separate switch configurations products to be released, an Ethernet Spectrum-X variant of the X800-Q3450 CPO switch with 102.4T aggregate bandwidth, the Spectrum 6810 offering 102.4T aggregate bandwidth, and its larger cousin the Spectrum 6800 offering 409.6T aggregate bandwidth by using four discrete Spectrum-6 multi-chip modules (MCMs).",
      "parent_source_html": null,
      "parent_inline_elements": [],
      "segment_start": 0,
      "segment_end": 414,
      "expected_tokens": [],
      "format_recovery_status": "not_applicable",
      "format_errors": [],
      "is_heading": false,
      "heading_level": null,
      "heading_chain": [],
      "is_metadata": false,
      "metadata_type": null,
      "translations": {},
      "confirmed": null,
      "confirmed_tokenized": null,
      "confirmed_format_issues": [],
      "status": "pending",
      "ai_insight": null,
      "history": []
    },
    {
      "id": "p025",
      "index": 25,
      "source": "The Quantum X800-Q3450 CPO switch utilizes four discrete switch packages connected to the physical in a multi-plane configuration, and each switch package is a monolithic die containing the 28.8T switch ASIC together with required SerDes and other electrical components. In contrast, Spectrum-X Photonics switch silicon is a multi-chip module (MCM) with a much larger reticle size 102.4T switch ASICs at the center, surrounded by eight 224G SerDes I/O chiplets – two on each side.",
      "source_html": null,
      "element_type": "p",
      "inline_elements": [],
      "parent_block_id": "b0378",
      "parent_block_index": 378,
      "parent_block_type": "p",
      "parent_block_markdown": "The Quantum X800-Q3450 CPO switch utilizes four discrete switch packages connected to the physical in a multi-plane configuration, and each switch package is a monolithic die containing the 28.8T switch ASIC together with required SerDes and other electrical components. In contrast, Spectrum-X Photonics switch silicon is a multi-chip module (MCM) with a much larger reticle size 102.4T switch ASICs at the center, surrounded by eight 224G SerDes I/O chiplets – two on each side.",
      "parent_block_plain_text": "The Quantum X800-Q3450 CPO switch utilizes four discrete switch packages connected to the physical in a multi-plane configuration, and each switch package is a monolithic die containing the 28.8T switch ASIC together with required SerDes and other electrical components. In contrast, Spectrum-X Photonics switch silicon is a multi-chip module (MCM) with a much larger reticle size 102.4T switch ASICs at the center, surrounded by eight 224G SerDes I/O chiplets – two on each side.",
      "parent_source_html": null,
      "parent_inline_elements": [],
      "segment_start": 0,
      "segment_end": 480,
      "expected_tokens": [],
      "format_recovery_status": "not_applicable",
      "format_errors": [],
      "is_heading": false,
      "heading_level": null,
      "heading_chain": [],
      "is_metadata": false,
      "metadata_type": null,
      "translations": {},
      "confirmed": null,
      "confirmed_tokenized": null,
      "confirmed_format_issues": [],
      "status": "pending",
      "ai_insight": null,
      "history": []
    },
    {
      "id": "p026",
      "index": 26,
      "source": "![](./Co_Packaged_Optics_(CPO)_–_Scaling_with_Light_for_the_Next_Wave_of_Interconnect_images/img_052.png)",
      "source_html": "<img src=\"![](./Co_Packaged_Optics_(CPO)_–_Scaling_with_Light_for_the_Next_Wave_of_Interconnect_images/img_052.png)\" />",
      "element_type": "image",
      "inline_elements": [],
      "parent_block_id": "b0379",
      "parent_block_index": 379,
      "parent_block_type": "image",
      "parent_block_markdown": "![](./Co_Packaged_Optics_(CPO)_–_Scaling_with_Light_for_the_Next_Wave_of_Interconnect_images/img_052.png)",
      "parent_block_plain_text": "![](./Co_Packaged_Optics_(CPO)_–_Scaling_with_Light_for_the_Next_Wave_of_Interconnect_images/img_052.png)",
      "parent_source_html": "<img src=\"![](./Co_Packaged_Optics_(CPO)_–_Scaling_with_Light_for_the_Next_Wave_of_Interconnect_images/img_052.png)\" />",
      "parent_inline_elements": [],
      "segment_start": 0,
      "segment_end": 105,
      "expected_tokens": [],
      "format_recovery_status": "not_applicable",
      "format_errors": [],
      "is_heading": false,
      "heading_level": null,
      "heading_chain": [],
      "is_metadata": true,
      "metadata_type": "image",
      "translations": {},
      "confirmed": "![](./Co_Packaged_Optics_(CPO)_–_Scaling_with_Light_for_the_Next_Wave_of_Interconnect_images/img_052.png)",
      "confirmed_tokenized": null,
      "confirmed_format_issues": [],
      "status": "approved",
      "ai_insight": null,
      "history": []
    },
    {
      "id": "p027",
      "index": 27,
      "source": "Source: Nvidia",
      "source_html": null,
      "element_type": "p",
      "inline_elements": [],
      "parent_block_id": "b0380",
      "parent_block_index": 380,
      "parent_block_type": "p",
      "parent_block_markdown": "Source: Nvidia",
      "parent_block_plain_text": "Source: Nvidia",
      "parent_source_html": null,
      "parent_inline_elements": [],
      "segment_start": 0,
      "segment_end": 14,
      "expected_tokens": [],
      "format_recovery_status": "not_applicable",
      "format_errors": [],
      "is_heading": false,
      "heading_level": null,
      "heading_chain": [],
      "is_metadata": true,
      "metadata_type": "source",
      "translations": {},
      "confirmed": null,
      "confirmed_tokenized": null,
      "confirmed_format_issues": [],
      "status": "pending",
      "ai_insight": null,
      "history": []
    },
    {
      "id": "p028",
      "index": 28,
      "source": "Each Spectrum-X photonics multi-chip module switch package will have 36 optical engines in a single 102.4T switch package. This package will use Nvidia’s second generation optical engine with 3.2T bandwidth, with each optical engine having 16 optical lanes of 200G each. Note that only 32 optical engines are active, with the additional 4 being there for redundancy purposes in case an OE fails. This is due to the OEs being soldered on the substrate, so they are not easily replaceable.",
      "source_html": null,
      "element_type": "p",
      "inline_elements": [],
      "parent_block_id": "b0381",
      "parent_block_index": 381,
      "parent_block_type": "p",
      "parent_block_markdown": "Each Spectrum-X photonics multi-chip module switch package will have 36 optical engines in a single 102.4T switch package. This package will use Nvidia’s second generation optical engine with 3.2T bandwidth, with each optical engine having 16 optical lanes of 200G each. Note that only 32 optical engines are active, with the additional 4 being there for redundancy purposes in case an OE fails. This is due to the OEs being soldered on the substrate, so they are not easily replaceable.",
      "parent_block_plain_text": "Each Spectrum-X photonics multi-chip module switch package will have 36 optical engines in a single 102.4T switch package. This package will use Nvidia’s second generation optical engine with 3.2T bandwidth, with each optical engine having 16 optical lanes of 200G each. Note that only 32 optical engines are active, with the additional 4 being there for redundancy purposes in case an OE fails. This is due to the OEs being soldered on the substrate, so they are not easily replaceable.",
      "parent_source_html": null,
      "parent_inline_elements": [],
      "segment_start": 0,
      "segment_end": 487,
      "expected_tokens": [],
      "format_recovery_status": "not_applicable",
      "format_errors": [],
      "is_heading": false,
      "heading_level": null,
      "heading_chain": [],
      "is_metadata": false,
      "metadata_type": null,
      "translations": {},
      "confirmed": null,
      "confirmed_tokenized": null,
      "confirmed_format_issues": [],
      "status": "pending",
      "ai_insight": null,
      "history": []
    },
    {
      "id": "p029",
      "index": 29,
      "source": "Each I/O chiplet delivers 12.8T of total unidirectional bandwidth, comprising of 64 SerDes lanes, and interfaces with 4 OEs each. This is what allows the Spectrum-X to deliver far more aggregate bandwidth than Quantum-X Photonics, with much more shoreline and area for the SerDes.",
      "source_html": null,
      "element_type": "p",
      "inline_elements": [],
      "parent_block_id": "b0382",
      "parent_block_index": 382,
      "parent_block_type": "p",
      "parent_block_markdown": "Each I/O chiplet delivers 12.8T of total unidirectional bandwidth, comprising of 64 SerDes lanes, and interfaces with 4 OEs each. This is what allows the Spectrum-X to deliver far more aggregate bandwidth than Quantum-X Photonics, with much more shoreline and area for the SerDes.",
      "parent_block_plain_text": "Each I/O chiplet delivers 12.8T of total unidirectional bandwidth, comprising of 64 SerDes lanes, and interfaces with 4 OEs each. This is what allows the Spectrum-X to deliver far more aggregate bandwidth than Quantum-X Photonics, with much more shoreline and area for the SerDes.",
      "parent_source_html": null,
      "parent_inline_elements": [],
      "segment_start": 0,
      "segment_end": 280,
      "expected_tokens": [],
      "format_recovery_status": "not_applicable",
      "format_errors": [],
      "is_heading": false,
      "heading_level": null,
      "heading_chain": [],
      "is_metadata": false,
      "metadata_type": null,
      "translations": {},
      "confirmed": null,
      "confirmed_tokenized": null,
      "confirmed_format_issues": [],
      "status": "pending",
      "ai_insight": null,
      "history": []
    },
    {
      "id": "p030",
      "index": 30,
      "source": "![](./Co_Packaged_Optics_(CPO)_–_Scaling_with_Light_for_the_Next_Wave_of_Interconnect_images/img_053.png)",
      "source_html": "<img src=\"![](./Co_Packaged_Optics_(CPO)_–_Scaling_with_Light_for_the_Next_Wave_of_Interconnect_images/img_053.png)\" />",
      "element_type": "image",
      "inline_elements": [],
      "parent_block_id": "b0383",
      "parent_block_index": 383,
      "parent_block_type": "image",
      "parent_block_markdown": "![](./Co_Packaged_Optics_(CPO)_–_Scaling_with_Light_for_the_Next_Wave_of_Interconnect_images/img_053.png)",
      "parent_block_plain_text": "![](./Co_Packaged_Optics_(CPO)_–_Scaling_with_Light_for_the_Next_Wave_of_Interconnect_images/img_053.png)",
      "parent_source_html": "<img src=\"![](./Co_Packaged_Optics_(CPO)_–_Scaling_with_Light_for_the_Next_Wave_of_Interconnect_images/img_053.png)\" />",
      "parent_inline_elements": [],
      "segment_start": 0,
      "segment_end": 105,
      "expected_tokens": [],
      "format_recovery_status": "not_applicable",
      "format_errors": [],
      "is_heading": false,
      "heading_level": null,
      "heading_chain": [],
      "is_metadata": true,
      "metadata_type": "image",
      "translations": {},
      "confirmed": "![](./Co_Packaged_Optics_(CPO)_–_Scaling_with_Light_for_the_Next_Wave_of_Interconnect_images/img_053.png)",
      "confirmed_tokenized": null,
      "confirmed_format_issues": [],
      "status": "approved",
      "ai_insight": null,
      "history": []
    },
    {
      "id": "p031",
      "index": 31,
      "source": "Source: SemiAnalysis",
      "source_html": null,
      "element_type": "p",
      "inline_elements": [],
      "parent_block_id": "b0384",
      "parent_block_index": 384,
      "parent_block_type": "p",
      "parent_block_markdown": "Source: SemiAnalysis",
      "parent_block_plain_text": "Source: SemiAnalysis",
      "parent_source_html": null,
      "parent_inline_elements": [],
      "segment_start": 0,
      "segment_end": 20,
      "expected_tokens": [],
      "format_recovery_status": "not_applicable",
      "format_errors": [],
      "is_heading": false,
      "heading_level": null,
      "heading_chain": [],
      "is_metadata": true,
      "metadata_type": "source",
      "translations": {},
      "confirmed": null,
      "confirmed_tokenized": null,
      "confirmed_format_issues": [],
      "status": "pending",
      "ai_insight": null,
      "history": []
    },
    {
      "id": "p032",
      "index": 32,
      "source": "The Spectrum-X 6810 Switch Box uses one unit of the above switch package to deliver 102.4T of aggregate bandwidth. The larger Spectrum-X 6800 Switch Box SKU is a high-density chassis with an aggregate bandwidth of 409.6T achieved by utilizing four of the above Spectrum-X switch packages which are also connected to the external physical ports in a multi-plane configuration.",
      "source_html": null,
      "element_type": "p",
      "inline_elements": [],
      "parent_block_id": "b0385",
      "parent_block_index": 385,
      "parent_block_type": "p",
      "parent_block_markdown": "The Spectrum-X 6810 Switch Box uses one unit of the above switch package to deliver 102.4T of aggregate bandwidth. The larger Spectrum-X 6800 Switch Box SKU is a high-density chassis with an aggregate bandwidth of 409.6T achieved by utilizing four of the above Spectrum-X switch packages which are also connected to the external physical ports in a multi-plane configuration.",
      "parent_block_plain_text": "The Spectrum-X 6810 Switch Box uses one unit of the above switch package to deliver 102.4T of aggregate bandwidth. The larger Spectrum-X 6800 Switch Box SKU is a high-density chassis with an aggregate bandwidth of 409.6T achieved by utilizing four of the above Spectrum-X switch packages which are also connected to the external physical ports in a multi-plane configuration.",
      "parent_source_html": null,
      "parent_inline_elements": [],
      "segment_start": 0,
      "segment_end": 375,
      "expected_tokens": [],
      "format_recovery_status": "not_applicable",
      "format_errors": [],
      "is_heading": false,
      "heading_level": null,
      "heading_chain": [],
      "is_metadata": false,
      "metadata_type": null,
      "translations": {},
      "confirmed": null,
      "confirmed_tokenized": null,
      "confirmed_format_issues": [],
      "status": "pending",
      "ai_insight": null,
      "history": []
    },
    {
      "id": "p033",
      "index": 33,
      "source": "![](./Co_Packaged_Optics_(CPO)_–_Scaling_with_Light_for_the_Next_Wave_of_Interconnect_images/img_054.png)",
      "source_html": "<img src=\"![](./Co_Packaged_Optics_(CPO)_–_Scaling_with_Light_for_the_Next_Wave_of_Interconnect_images/img_054.png)\" />",
      "element_type": "image",
      "inline_elements": [],
      "parent_block_id": "b0386",
      "parent_block_index": 386,
      "parent_block_type": "image",
      "parent_block_markdown": "![](./Co_Packaged_Optics_(CPO)_–_Scaling_with_Light_for_the_Next_Wave_of_Interconnect_images/img_054.png)",
      "parent_block_plain_text": "![](./Co_Packaged_Optics_(CPO)_–_Scaling_with_Light_for_the_Next_Wave_of_Interconnect_images/img_054.png)",
      "parent_source_html": "<img src=\"![](./Co_Packaged_Optics_(CPO)_–_Scaling_with_Light_for_the_Next_Wave_of_Interconnect_images/img_054.png)\" />",
      "parent_inline_elements": [],
      "segment_start": 0,
      "segment_end": 105,
      "expected_tokens": [],
      "format_recovery_status": "not_applicable",
      "format_errors": [],
      "is_heading": false,
      "heading_level": null,
      "heading_chain": [],
      "is_metadata": true,
      "metadata_type": "image",
      "translations": {},
      "confirmed": "![](./Co_Packaged_Optics_(CPO)_–_Scaling_with_Light_for_the_Next_Wave_of_Interconnect_images/img_054.png)",
      "confirmed_tokenized": null,
      "confirmed_format_issues": [],
      "status": "approved",
      "ai_insight": null,
      "history": []
    },
    {
      "id": "p034",
      "index": 34,
      "source": "Source: Nvidia",
      "source_html": null,
      "element_type": "p",
      "inline_elements": [],
      "parent_block_id": "b0387",
      "parent_block_index": 387,
      "parent_block_type": "p",
      "parent_block_markdown": "Source: Nvidia",
      "parent_block_plain_text": "Source: Nvidia",
      "parent_source_html": null,
      "parent_inline_elements": [],
      "segment_start": 0,
      "segment_end": 14,
      "expected_tokens": [],
      "format_recovery_status": "not_applicable",
      "format_errors": [],
      "is_heading": false,
      "heading_level": null,
      "heading_chain": [],
      "is_metadata": true,
      "metadata_type": "source",
      "translations": {},
      "confirmed": null,
      "confirmed_tokenized": null,
      "confirmed_format_issues": [],
      "status": "pending",
      "ai_insight": null,
      "history": []
    },
    {
      "id": "p035",
      "index": 35,
      "source": "Much like the four ASIC 115.2T Quantum X800-Q3450, the Spectrum-X 6800 uses an internal breakout to physically connect each port to all four ASICs.",
      "source_html": null,
      "element_type": "p",
      "inline_elements": [],
      "parent_block_id": "b0388",
      "parent_block_index": 388,
      "parent_block_type": "p",
      "parent_block_markdown": "Much like the four ASIC 115.2T Quantum X800-Q3450, the Spectrum-X 6800 uses an internal breakout to physically connect each port to all four ASICs.",
      "parent_block_plain_text": "Much like the four ASIC 115.2T Quantum X800-Q3450, the Spectrum-X 6800 uses an internal breakout to physically connect each port to all four ASICs.",
      "parent_source_html": null,
      "parent_inline_elements": [],
      "segment_start": 0,
      "segment_end": 147,
      "expected_tokens": [],
      "format_recovery_status": "not_applicable",
      "format_errors": [],
      "is_heading": false,
      "heading_level": null,
      "heading_chain": [],
      "is_metadata": false,
      "metadata_type": null,
      "translations": {},
      "confirmed": null,
      "confirmed_tokenized": null,
      "confirmed_format_issues": [],
      "status": "pending",
      "ai_insight": null,
      "history": []
    },
    {
      "id": "p036",
      "index": 36,
      "source": "![](./Co_Packaged_Optics_(CPO)_–_Scaling_with_Light_for_the_Next_Wave_of_Interconnect_images/img_055.png)",
      "source_html": "<img src=\"![](./Co_Packaged_Optics_(CPO)_–_Scaling_with_Light_for_the_Next_Wave_of_Interconnect_images/img_055.png)\" />",
      "element_type": "image",
      "inline_elements": [],
      "parent_block_id": "b0389",
      "parent_block_index": 389,
      "parent_block_type": "image",
      "parent_block_markdown": "![](./Co_Packaged_Optics_(CPO)_–_Scaling_with_Light_for_the_Next_Wave_of_Interconnect_images/img_055.png)",
      "parent_block_plain_text": "![](./Co_Packaged_Optics_(CPO)_–_Scaling_with_Light_for_the_Next_Wave_of_Interconnect_images/img_055.png)",
      "parent_source_html": "<img src=\"![](./Co_Packaged_Optics_(CPO)_–_Scaling_with_Light_for_the_Next_Wave_of_Interconnect_images/img_055.png)\" />",
      "parent_inline_elements": [],
      "segment_start": 0,
      "segment_end": 105,
      "expected_tokens": [],
      "format_recovery_status": "not_applicable",
      "format_errors": [],
      "is_heading": false,
      "heading_level": null,
      "heading_chain": [],
      "is_metadata": true,
      "metadata_type": "image",
      "translations": {},
      "confirmed": "![](./Co_Packaged_Optics_(CPO)_–_Scaling_with_Light_for_the_Next_Wave_of_Interconnect_images/img_055.png)",
      "confirmed_tokenized": null,
      "confirmed_format_issues": [],
      "status": "approved",
      "ai_insight": null,
      "history": []
    },
    {
      "id": "p037",
      "index": 37,
      "source": "Source: SemiAnalysis",
      "source_html": null,
      "element_type": "p",
      "inline_elements": [],
      "parent_block_id": "b0390",
      "parent_block_index": 390,
      "parent_block_type": "p",
      "parent_block_markdown": "Source: SemiAnalysis",
      "parent_block_plain_text": "Source: SemiAnalysis",
      "parent_source_html": null,
      "parent_inline_elements": [],
      "segment_start": 0,
      "segment_end": 20,
      "expected_tokens": [],
      "format_recovery_status": "not_applicable",
      "format_errors": [],
      "is_heading": false,
      "heading_level": null,
      "heading_chain": [],
      "is_metadata": true,
      "metadata_type": "source",
      "translations": {},
      "confirmed": null,
      "confirmed_tokenized": null,
      "confirmed_format_issues": [],
      "status": "pending",
      "ai_insight": null,
      "history": []
    }
  ]
}